setup.py
codepad/__init__.py
codepad.egg-info/PKG-INFO
codepad.egg-info/SOURCES.txt
codepad.egg-info/dependency_links.txt
codepad.egg-info/requires.txt
codepad.egg-info/top_level.txt
scripts/codepad