Metadata-Version: 1.0
Name: codepad
Version: 0.1
Summary: A Command line interface for codepad.org
Home-page: https://github.com/daltonmatos/codepad
Author: Dalton Barreto
Author-email: daltonmatos@gmail.com
License: 3-clause BSD
Platform: UNKNOWN
Classifier: Operating System :: OS Independent
Classifier: Programming Language :: Python
